geometrical_layout/__init__.py
geometrical_layout/exceptions.py
geometrical_layout/geometrical_layout.py
geometrical_layout/version.py
geometrical_layout-0.1.0.dist-info/LICENSE
geometrical_layout-0.1.0.dist-info/METADATA
geometrical_layout-0.1.0.dist-info/WHEEL
geometrical_layout-0.1.0.dist-info/top_level.txt
geometrical_layout-0.1.0.dist-info/RECORD
