Metadata-Version: 2.1
Name: geometrical-layout
Version: 0.1.0
Summary: This client library is designed to help query endpoints of the "Dowell Geometrical Layout of Big Data API"
Home-page: https://github.com/DoWellUXLab/DoWell-Geometrical-layout-of-Big-Data
Maintainer: Abdullahi Abdulwasiu
Maintainer-email: abdullahiabdulwasiu1@gmail.com
License: Apache
Platform: UNKNOWN
Classifier: License :: OSI Approved :: Apache Software License
Classifier: Programming Language :: Python
Classifier: Programming Language :: Python :: 3
Classifier: Programming Language :: Python :: 3.5
Classifier: Programming Language :: Python :: 3.6
Classifier: Programming Language :: Python :: 3.7
Classifier: Programming Language :: Python :: 3.8
Requires-Dist: requests
